{"inkVersion":20,"root":[[{"->":"Guest_32"},["done",{"#f":5,"#n":"g-0"}],null],"done",{"Guest_32":["^GUEST_WOMAN: Здравствуйте.","\n","^THOMAS: Добро пожаловать. Мы рады дамам в этом заведении.","\n","^THOMAS: Что желаете?","\n","^GUEST_WOMAN: Найдется <alc_PERFECTROBROY>Идеальный Роб Рой</alc>?","\n",{"->":"Order"},{"#f":1}],"Order":[[{"#":"check"},["ev",{"^->":"Order.0.1.$r1"},{"temp=":"$r"},"str",{"->":".^.s"},[{"#n":"$r1"}],"/str","/ev",{"*":".^.^.c-0","flg":18},{"s":["^THOMAS: У вас прекрасный вкус... Сделаю вам самый лучшего Роба.",{"->":"$r","var":true},null]}],["ev",{"^->":"Order.0.2.$r1"},{"temp=":"$r"},"str",{"->":".^.s"},[{"#n":"$r1"}],"/str","/ev",{"*":".^.^.c-1","flg":18},{"s":["^THOMAS: Для прекрасной дамы больше подойдет <alc_ANYTHING></alc>.",{"->":"$r","var":true},null]}],["ev",{"^->":"Order.0.3.$r1"},{"temp=":"$r"},"str",{"->":".^.s"},[{"#n":"$r1"}],"/str","/ev",{"*":".^.^.c-2","flg":18},{"s":["^THOMAS: Вынужден вас огрочить, но я не могу приготовить вам этот напиток. Могу предложить на замену <alc_ANYTHING></alc>.",{"->":"$r","var":true},null]}],{"c-0":["ev",{"^->":"Order.0.c-0.$r2"},"/ev",{"temp=":"$r"},{"->":".^.^.1.s"},[{"#n":"$r2"}],"\n","^GUEST_WOMAN: Я в этом не сомневаюсь...","\n",{"#":"order"},"^THOMAS: Прошу...","\n",{"->":"Grade"},{"#f":5}],"c-1":["ev",{"^->":"Order.0.c-1.$r2"},"/ev",{"temp=":"$r"},{"->":".^.^.2.s"},[{"#n":"$r2"}],"\n",{"#":"guestchoice"},[["ev",{"^->":"Order.0.c-1.8.0.$r1"},{"temp=":"$r"},"str",{"->":".^.s"},[{"#n":"$r1"}],"/str","/ev",{"*":".^.^.c-0","flg":18},{"s":["^GUEST_WOMAN: Полностью доверюсь вашему вкусу...",{"->":"$r","var":true},null]}],["ev",{"^->":"Order.0.c-1.8.1.$r1"},{"temp=":"$r"},"str",{"->":".^.s"},[{"#n":"$r1"}],"/str","/ev",{"*":".^.^.c-1","flg":18},{"s":["^GUEST_WOMAN: Я в тебе не сомневаюсь, но сегодня не день экспериментов.",{"->":"$r","var":true},null]}],{"c-0":["ev",{"^->":"Order.0.c-1.8.c-0.$r2"},"/ev",{"temp=":"$r"},{"->":".^.^.0.s"},[{"#n":"$r2"}],"\n",{"#":"order"},"^THOMAS: Прошу, ваш напиток.","\n",{"->":"Grade"},{"#f":5}],"c-1":["ev",{"^->":"Order.0.c-1.8.c-1.$r2"},"/ev",{"temp=":"$r"},{"->":".^.^.1.s"},[{"#n":"$r2"}],"\n","^THOMAS: Мои извинения.","\n",{"#":"order"},"^THOMAS: Прошу...","\n",{"->":"Grade"},{"#f":5}]}],{"#f":5}],"c-2":["ev",{"^->":"Order.0.c-2.$r2"},"/ev",{"temp=":"$r"},{"->":".^.^.3.s"},[{"#n":"$r2"}],"\n","^THOMAS: Вынужден вас огрочить, но я не могу приготовить вам этот напиток. Могу предложить на замену <alc_ANYTHING></alc>.","\n",{"#":"guestchoice"},[["ev",{"^->":"Order.0.c-2.10.0.$r1"},{"temp=":"$r"},"str",{"->":".^.s"},[{"#n":"$r1"}],"/str","/ev",{"*":".^.^.c-0","flg":18},{"s":["^GUEST_WOMAN: Полностью доверюсь вашему вкусу...",{"->":"$r","var":true},null]}],["ev",{"^->":"Order.0.c-2.10.1.$r1"},{"temp=":"$r"},"str",{"->":".^.s"},[{"#n":"$r1"}],"/str","/ev",{"*":".^.^.c-1","flg":18},{"s":["^GUEST_WOMAN: Очень жаль. Мне хотелось именно чего-то такого вкусненького...",{"->":"$r","var":true},null]}],{"c-0":["ev",{"^->":"Order.0.c-2.10.c-0.$r2"},"/ev",{"temp=":"$r"},{"->":".^.^.0.s"},[{"#n":"$r2"}],"\n",{"#":"order"},"^THOMAS: Прошу, ваш напиток.","\n",{"->":"Grade"},{"#f":5}],"c-1":["ev",{"^->":"Order.0.c-2.10.c-1.$r2"},"/ev",{"temp=":"$r"},{"->":".^.^.1.s"},[{"#n":"$r2"}],"\n","^THOMAS: Сожалею, но не сегодня. ","end","\n",{"#f":5}]}],{"#f":5}]}],{"#f":1}],"Grade":[[{"#":"grade"},["ev",{"^->":"Grade.0.1.$r1"},{"temp=":"$r"},"str",{"->":".^.s"},[{"#n":"$r1"}],"/str","/ev",{"*":".^.^.c-0","flg":18},{"s":["^GUEST_WOMAN: Прекрасно! А вы знаете своё дело.",{"->":"$r","var":true},null]}],["ev",{"^->":"Grade.0.2.$r1"},{"temp=":"$r"},"str",{"->":".^.s"},[{"#n":"$r1"}],"/str","/ev",{"*":".^.^.c-1","flg":18},{"s":["^GUEST_WOMAN: Благодарю. Неплохо получилось.",{"->":"$r","var":true},null]}],["ev",{"^->":"Grade.0.3.$r1"},{"temp=":"$r"},"str",{"->":".^.s"},[{"#n":"$r1"}],"/str","/ev",{"*":".^.^.c-2","flg":18},{"s":["^GUEST_WOMAN: Вам не хватает опыта в этом деле. Но... Пожалуй, я сделаю вам одолжение и вернусь сюда снова. Не подведите меня.",{"->":"$r","var":true},null]}],{"c-0":["ev",{"^->":"Grade.0.c-0.$r2"},"/ev",{"temp=":"$r"},{"->":".^.^.1.s"},[{"#n":"$r2"}],"\n",{"->":".^.^.g-0"},{"#f":5}],"c-1":["ev",{"^->":"Grade.0.c-1.$r2"},"/ev",{"temp=":"$r"},{"->":".^.^.2.s"},[{"#n":"$r2"}],"\n",{"->":".^.^.g-0"},{"#f":5}],"c-2":["ev",{"^->":"Grade.0.c-2.$r2"},"/ev",{"temp=":"$r"},{"->":".^.^.3.s"},[{"#n":"$r2"}],"\n",{"->":".^.^.g-0"},{"#f":5}],"g-0":["end",{"#f":5}]}],{"#f":1}],"#f":1}],"listDefs":{}}